{
    "boardWidth": 2544,
    "boardHeight": 1927,
    "numberRows": 3,
    "numberColumns": 4,
    "x1": 410,
    "x2": 2144,
    "y1": 394,
    "y2": 1715,
    "ammoTileWidth": 100,
    "ammoTileHeight": 100,
    "ammoTiles": [
        {
            "row": 0,
            "col": 0,
            "x": 514,
            "y": 482
        },
        {
            "row": 0,
            "col": 1,
            "x": 908,
            "y": 675
        },
        {
            "row": 1,
            "col": 1,
            "x": 872,
            "y": 998
        },
        {
            "row": 1,
            "col": 2,
            "x": 1371,
            "y": 1055
        },
        {
            "row": 1,
            "col": 3,
            "x": 1947,
            "y": 1053
        },
        {
            "row": 2,
            "col": 1,
            "x": 884,
            "y": 1502
        },
        {
            "row": 0,
            "col": 0,
            "x": 1321,
            "y": 1501
        }
    ]
}
